pywannamaker/__init__.py
pywannamaker/config.py
pywannamaker/enum.py
pywannamaker/event.py
pywannamaker/map.py
pywannamaker/object.py
pywannamaker/parser.py
pywannamaker/properties.py
pywannamaker-0.0.4.dist-info/METADATA
pywannamaker-0.0.4.dist-info/WHEEL
pywannamaker-0.0.4.dist-info/licenses/LICENSE
pywannamaker-0.0.4.dist-info/RECORD
