Metadata-Version: 2.1
Name: pywannamaker
Version: 0.0.4
Summary: A parser for I Wanna Maker maps
Project-URL: Homepage, https://github.com/iwVerve/pywm
Project-URL: Bug Tracker, https://github.com/iwVerve/pywm/issues
Author-email: iwVerve <thedolphiner@gmail.com>
License: MIT License
Classifier: License :: OSI Approved :: MIT License
Classifier: Operating System :: OS Independent
Classifier: Programming Language :: Python :: 3
Requires-Python: >=3.7
